djongo/__init__.py
djongo/admin.py
djongo/base.py
djongo/compiler.py
djongo/creation.py
djongo/cursor.py
djongo/database.py
djongo/exceptions.py
djongo/features.py
djongo/introspection.py
djongo/operations.py
djongo/schema.py
djongo/storage.py
djongo/transaction.py
djongo/models/__init__.py
djongo/models/fields.py
djongo/models/indexes.py
djongo/models/json.py
djongo/sql2mongo/__init__.py
djongo/sql2mongo/aggregation.py
djongo/sql2mongo/constraints.py
djongo/sql2mongo/converters.py
djongo/sql2mongo/functions.py
djongo/sql2mongo/operators.py
djongo/sql2mongo/query.py
djongo/sql2mongo/sql_tokens.py
djongo/sql2mongo/validation.py
dj_mongo_backend-0.1.4.dist-info/LICENSE
dj_mongo_backend-0.1.4.dist-info/METADATA
dj_mongo_backend-0.1.4.dist-info/WHEEL
dj_mongo_backend-0.1.4.dist-info/top_level.txt
dj_mongo_backend-0.1.4.dist-info/RECORD
